{
  "timestamp": "2026-05-22T22:56:29.460241",
  "period": "5d",
  "series": [
    {
      "name": "Technology",
      "data": [
        {
          "x": "NVDA",
          "y": 35947440288.0,
          "price": 215.33,
          "change": -1.9,
          "color": "#F44336"
        },
        {
          "x": "AMD",
          "y": 16181051127.0,
          "price": 467.51,
          "change": 3.99,
          "color": "#00C853"
        },
        {
          "x": "AAPL",
          "y": 13466115875.0,
          "price": 308.82,
          "change": 1.26,
          "color": "#4CAF50"
        },
        {
          "x": "MSFT",
          "y": 9171575407.0,
          "price": 418.57,
          "change": -0.12,
          "color": "#EF9A9A"
        },
        {
          "x": "AVGO",
          "y": 5805222564.0,
          "price": 414.14,
          "change": -0.1,
          "color": "#EF9A9A"
        },
        {
          "x": "ORCL",
          "y": 1818591944.0,
          "price": 192.08,
          "change": 1.22,
          "color": "#4CAF50"
        },
        {
          "x": "CRM",
          "y": 1797310976.0,
          "price": 180.07,
          "change": 2.13,
          "color": "#4CAF50"
        },
        {
          "x": "ADBE",
          "y": 924715252.0,
          "price": 244.76,
          "change": 0.27,
          "color": "#81C784"
        }
      ]
    },
    {
      "name": "Consumer Disc.",
      "data": [
        {
          "x": "TSLA",
          "y": 19199617641.0,
          "price": 426.01,
          "change": 1.95,
          "color": "#4CAF50"
        },
        {
          "x": "AMZN",
          "y": 7027336764.0,
          "price": 266.32,
          "change": -0.8,
          "color": "#EF9A9A"
        },
        {
          "x": "SBUX",
          "y": 927067068.0,
          "price": 103.11,
          "change": -0.98,
          "color": "#EF9A9A"
        },
        {
          "x": "HD",
          "y": 926520668.0,
          "price": 313.07,
          "change": -0.23,
          "color": "#EF9A9A"
        },
        {
          "x": "NKE",
          "y": 650565321.0,
          "price": 44.67,
          "change": 0.63,
          "color": "#81C784"
        },
        {
          "x": "LOW",
          "y": 602295801.0,
          "price": 215.03,
          "change": -1.09,
          "color": "#F44336"
        },
        {
          "x": "MCD",
          "y": 598816870.0,
          "price": 282.27,
          "change": -0.67,
          "color": "#EF9A9A"
        },
        {
          "x": "TJX",
          "y": 573196187.0,
          "price": 158.27,
          "change": 0.51,
          "color": "#81C784"
        }
      ]
    },
    {
      "name": "Comm. Services",
      "data": [
        {
          "x": "GOOGL",
          "y": 7328055145.0,
          "price": 382.97,
          "change": -1.21,
          "color": "#F44336"
        },
        {
          "x": "META",
          "y": 6775735196.0,
          "price": 610.26,
          "change": 0.47,
          "color": "#81C784"
        },
        {
          "x": "NFLX",
          "y": 2100625426.0,
          "price": 88.6,
          "change": -0.78,
          "color": "#EF9A9A"
        },
        {
          "x": "VZ",
          "y": 706609215.0,
          "price": 48.35,
          "change": 0.17,
          "color": "#81C784"
        },
        {
          "x": "CMCSA",
          "y": 669733219.0,
          "price": 25.2,
          "change": 0.5,
          "color": "#81C784"
        },
        {
          "x": "T",
          "y": 539841190.0,
          "price": 25.26,
          "change": -0.32,
          "color": "#EF9A9A"
        },
        {
          "x": "DIS",
          "y": 395557389.0,
          "price": 103.0,
          "change": -0.56,
          "color": "#EF9A9A"
        },
        {
          "x": "CHTR",
          "y": 302291845.0,
          "price": 145.15,
          "change": -2.52,
          "color": "#F44336"
        }
      ]
    },
    {
      "name": "Financials",
      "data": [
        {
          "x": "V",
          "y": 2453794765.0,
          "price": 328.88,
          "change": -0.68,
          "color": "#EF9A9A"
        },
        {
          "x": "BRK-B",
          "y": 2093414560.0,
          "price": 486.38,
          "change": 1.33,
          "color": "#4CAF50"
        },
        {
          "x": "GS",
          "y": 1916422701.0,
          "price": 996.73,
          "change": 0.87,
          "color": "#81C784"
        },
        {
          "x": "JPM",
          "y": 1344774147.0,
          "price": 306.38,
          "change": 1.12,
          "color": "#4CAF50"
        },
        {
          "x": "BAC",
          "y": 1046926987.0,
          "price": 51.8,
          "change": 0.6,
          "color": "#81C784"
        },
        {
          "x": "MA",
          "y": 976547148.0,
          "price": 498.54,
          "change": -0.22,
          "color": "#EF9A9A"
        },
        {
          "x": "WFC",
          "y": 666795529.0,
          "price": 76.4,
          "change": 0.63,
          "color": "#81C784"
        },
        {
          "x": "MS",
          "y": 599260777.0,
          "price": 201.03,
          "change": 0.26,
          "color": "#81C784"
        }
      ]
    },
    {
      "name": "Healthcare",
      "data": [
        {
          "x": "LLY",
          "y": 2928619005.0,
          "price": 1065.0,
          "change": 2.24,
          "color": "#4CAF50"
        },
        {
          "x": "UNH",
          "y": 2102915535.0,
          "price": 388.47,
          "change": 1.57,
          "color": "#4CAF50"
        },
        {
          "x": "MRK",
          "y": 1498200150.0,
          "price": 122.41,
          "change": 5.64,
          "color": "#00C853"
        },
        {
          "x": "JNJ",
          "y": 1279665339.0,
          "price": 234.34,
          "change": 1.13,
          "color": "#4CAF50"
        },
        {
          "x": "ABBV",
          "y": 857216809.0,
          "price": 215.7,
          "change": 0.56,
          "color": "#81C784"
        },
        {
          "x": "ABT",
          "y": 695046850.0,
          "price": 87.41,
          "change": -0.41,
          "color": "#EF9A9A"
        },
        {
          "x": "TMO",
          "y": 631493379.0,
          "price": 448.28,
          "change": -0.24,
          "color": "#EF9A9A"
        },
        {
          "x": "PFE",
          "y": 452645928.0,
          "price": 25.9,
          "change": -0.19,
          "color": "#EF9A9A"
        }
      ]
    },
    {
      "name": "Consumer Staples",
      "data": [
        {
          "x": "WMT",
          "y": 3641359725.0,
          "price": 120.27,
          "change": -0.88,
          "color": "#EF9A9A"
        },
        {
          "x": "COST",
          "y": 2054959214.0,
          "price": 1028.24,
          "change": -2.11,
          "color": "#F44336"
        },
        {
          "x": "PEP",
          "y": 947070289.0,
          "price": 150.57,
          "change": 1.16,
          "color": "#4CAF50"
        },
        {
          "x": "PG",
          "y": 666702697.0,
          "price": 144.44,
          "change": 0.73,
          "color": "#81C784"
        },
        {
          "x": "KO",
          "y": 657202144.0,
          "price": 81.48,
          "change": 0.38,
          "color": "#81C784"
        },
        {
          "x": "PM",
          "y": 450759495.0,
          "price": 188.99,
          "change": 0.28,
          "color": "#81C784"
        },
        {
          "x": "MO",
          "y": 332204229.0,
          "price": 73.9,
          "change": 0.26,
          "color": "#81C784"
        },
        {
          "x": "CL",
          "y": 235609651.0,
          "price": 90.61,
          "change": 0.19,
          "color": "#81C784"
        }
      ]
    },
    {
      "name": "Industrials",
      "data": [
        {
          "x": "CAT",
          "y": 1748512158.0,
          "price": 879.89,
          "change": 1.61,
          "color": "#4CAF50"
        },
        {
          "x": "HON",
          "y": 1155676784.0,
          "price": 227.92,
          "change": 1.84,
          "color": "#4CAF50"
        },
        {
          "x": "DE",
          "y": 927913779.0,
          "price": 529.15,
          "change": -0.41,
          "color": "#EF9A9A"
        },
        {
          "x": "BA",
          "y": 841997438.0,
          "price": 219.02,
          "change": -0.27,
          "color": "#EF9A9A"
        },
        {
          "x": "GE",
          "y": 828300400.0,
          "price": 302.84,
          "change": 0.36,
          "color": "#81C784"
        },
        {
          "x": "RTX",
          "y": 721449193.0,
          "price": 177.01,
          "change": 0.59,
          "color": "#81C784"
        },
        {
          "x": "UNP",
          "y": 582558512.0,
          "price": 265.88,
          "change": 0.17,
          "color": "#81C784"
        },
        {
          "x": "MMM",
          "y": 489170364.0,
          "price": 152.44,
          "change": 0.55,
          "color": "#81C784"
        }
      ]
    },
    {
      "name": "Energy",
      "data": [
        {
          "x": "XOM",
          "y": 2001281788.0,
          "price": 154.92,
          "change": -0.24,
          "color": "#EF9A9A"
        },
        {
          "x": "CVX",
          "y": 1024823912.0,
          "price": 191.43,
          "change": 0.22,
          "color": "#81C784"
        },
        {
          "x": "VLO",
          "y": 614982525.0,
          "price": 246.96,
          "change": 2.43,
          "color": "#4CAF50"
        },
        {
          "x": "MPC",
          "y": 486338707.0,
          "price": 254.65,
          "change": 2.5,
          "color": "#4CAF50"
        },
        {
          "x": "COP",
          "y": 484884502.0,
          "price": 120.46,
          "change": -0.07,
          "color": "#EF9A9A"
        },
        {
          "x": "SLB",
          "y": 394317975.0,
          "price": 57.28,
          "change": 0.05,
          "color": "#81C784"
        },
        {
          "x": "EOG",
          "y": 287436084.0,
          "price": 141.22,
          "change": 0.89,
          "color": "#81C784"
        },
        {
          "x": "PSX",
          "y": 273460827.0,
          "price": 177.69,
          "change": 2.09,
          "color": "#4CAF50"
        }
      ]
    },
    {
      "name": "Materials",
      "data": [
        {
          "x": "LIN",
          "y": 683506854.0,
          "price": 517.58,
          "change": 0.6,
          "color": "#81C784"
        },
        {
          "x": "NEM",
          "y": 538678995.0,
          "price": 107.64,
          "change": -0.64,
          "color": "#EF9A9A"
        },
        {
          "x": "FCX",
          "y": 485877013.0,
          "price": 61.99,
          "change": -0.51,
          "color": "#EF9A9A"
        },
        {
          "x": "SHW",
          "y": 383131842.0,
          "price": 309.08,
          "change": -0.08,
          "color": "#EF9A9A"
        },
        {
          "x": "DOW",
          "y": 324417712.0,
          "price": 36.01,
          "change": 0.28,
          "color": "#81C784"
        },
        {
          "x": "NUE",
          "y": 259596632.0,
          "price": 232.0,
          "change": 2.46,
          "color": "#4CAF50"
        },
        {
          "x": "APD",
          "y": 238491439.0,
          "price": 289.47,
          "change": -0.25,
          "color": "#EF9A9A"
        },
        {
          "x": "DD",
          "y": 109546477.0,
          "price": 48.12,
          "change": 2.06,
          "color": "#4CAF50"
        }
      ]
    },
    {
      "name": "Utilities",
      "data": [
        {
          "x": "NEE",
          "y": 795789845.0,
          "price": 88.55,
          "change": -1.27,
          "color": "#F44336"
        },
        {
          "x": "AEP",
          "y": 431655455.0,
          "price": 131.59,
          "change": 1.53,
          "color": "#4CAF50"
        },
        {
          "x": "EXC",
          "y": 426617925.0,
          "price": 46.23,
          "change": 1.94,
          "color": "#4CAF50"
        },
        {
          "x": "D",
          "y": 423600993.0,
          "price": 67.67,
          "change": -0.91,
          "color": "#EF9A9A"
        },
        {
          "x": "XEL",
          "y": 291235961.0,
          "price": 81.08,
          "change": 1.1,
          "color": "#4CAF50"
        },
        {
          "x": "DUK",
          "y": 219693400.0,
          "price": 125.67,
          "change": 0.81,
          "color": "#81C784"
        },
        {
          "x": "SO",
          "y": 203342546.0,
          "price": 94.55,
          "change": 0.33,
          "color": "#81C784"
        },
        {
          "x": "SRE",
          "y": 139481560.0,
          "price": 92.8,
          "change": 1.37,
          "color": "#4CAF50"
        }
      ]
    },
    {
      "name": "Real Estate",
      "data": [
        {
          "x": "EQIX",
          "y": 459911732.0,
          "price": 1079.79,
          "change": 0.13,
          "color": "#81C784"
        },
        {
          "x": "AMT",
          "y": 380547083.0,
          "price": 183.85,
          "change": 0.04,
          "color": "#81C784"
        },
        {
          "x": "WELL",
          "y": 335616460.0,
          "price": 216.17,
          "change": 0.07,
          "color": "#81C784"
        },
        {
          "x": "O",
          "y": 268608994.0,
          "price": 62.02,
          "change": -0.34,
          "color": "#EF9A9A"
        },
        {
          "x": "CCI",
          "y": 238203178.0,
          "price": 91.46,
          "change": -0.63,
          "color": "#EF9A9A"
        },
        {
          "x": "SPG",
          "y": 235451298.0,
          "price": 204.41,
          "change": -0.24,
          "color": "#EF9A9A"
        },
        {
          "x": "PLD",
          "y": 205712280.0,
          "price": 145.9,
          "change": 0.88,
          "color": "#81C784"
        },
        {
          "x": "PSA",
          "y": 150151559.0,
          "price": 305.25,
          "change": 0.09,
          "color": "#81C784"
        }
      ]
    }
  ]
}