{
  "timestamp": "2026-07-20T22:58:34.363442",
  "period": "5d",
  "sectors": [
    {
      "ticker": "XLE",
      "name": "Energy",
      "color": "#FF6347",
      "price": 57.94,
      "change_1d": 0.45,
      "change_period": 1.74
    },
    {
      "ticker": "XLC",
      "name": "Comm. Services",
      "color": "#9370DB",
      "price": 110.8,
      "change_1d": 0.14,
      "change_period": -0.58
    },
    {
      "ticker": "XLK",
      "name": "Technology",
      "color": "#4A90A4",
      "price": 175.71,
      "change_1d": 0.07,
      "change_period": -4.31
    },
    {
      "ticker": "XLF",
      "name": "Financials",
      "color": "#6B8E23",
      "price": 56.04,
      "change_1d": -0.39,
      "change_period": -0.25
    },
    {
      "ticker": "XLP",
      "name": "Consumer Staples",
      "color": "#98D8C8",
      "price": 84.86,
      "change_1d": -0.39,
      "change_period": 1.73
    },
    {
      "ticker": "XLRE",
      "name": "Real Estate",
      "color": "#CD853F",
      "price": 45.23,
      "change_1d": -0.42,
      "change_period": 1.69
    },
    {
      "ticker": "XLU",
      "name": "Utilities",
      "color": "#87CEEB",
      "price": 44.94,
      "change_1d": -0.51,
      "change_period": -1.64
    },
    {
      "ticker": "XLY",
      "name": "Consumer Disc.",
      "color": "#FFD700",
      "price": 114.61,
      "change_1d": -0.72,
      "change_period": -1.11
    },
    {
      "ticker": "XLI",
      "name": "Industrials",
      "color": "#DDA0DD",
      "price": 178.12,
      "change_1d": -0.72,
      "change_period": -1.29
    },
    {
      "ticker": "XLB",
      "name": "Materials",
      "color": "#F0E68C",
      "price": 50.03,
      "change_1d": -0.99,
      "change_period": -1.2
    },
    {
      "ticker": "XLV",
      "name": "Healthcare",
      "color": "#FF69B4",
      "price": 159.25,
      "change_1d": -1.14,
      "change_period": 0.61
    }
  ]
}